[
    {
        "id": 1,
        "image": "/img/products/f1.jpg",
        "create": "Malmö",
        "name": "Sunflowers Shirt",
        "price": 38.99,
        "currency": "$",
        "category": "Shirts"
    },
    {
        "id": 2,
        "image": "/img/products/f2.jpg",
        "create": "Malmö",
        "name": "Coconut Beach Shirts",
        "price": 38.99,
        "currency": "$",
        "category": "Shirts"
    },
    {
        "id": 3,
        "image": "/img/products/f3.jpg",
        "create": "Malmö",
        "name": "Cést La Vie T-Shirt",
        "price": 18.99,
        "currency": "$",
        "category": "T-Shirts"
    },
    {
        "id": 4,
        "image": "/img/products/f4.jpg",
        "create": "Malmö",
        "name": "Mawi T-Shirt",
        "price": 18.99,
        "currency": "$",
        "category": "T-Shirts"
    },
    {
        "id": 5,
        "image": "/img/products/f5.jpg",
        "create": "Malmö",
        "name": "Pineapple Shirts",
        "price": 38.99,
        "currency": "$",
        "category": "Shirts"
    },
    {
        "id": 6,
        "image": "/img/products/f6.jpg",
        "create": "Malmö",
        "name": "Multi-Brown Jacket",
        "price": 52.99,
        "currency": "$",
        "category": "Jackets"
    },
    {
        "id": 7,
        "image": "/img/products/f7.jpg",
        "create": "Malmö",
        "name": "Stockholm Jacket",
        "price": 52.99,
        "currency": "$",
        "category": "Jackets"
    },
    {
        "id": 8,
        "image": "/img/products/f8.jpg",
        "create": "Malmö",
        "name": "Classic Trousers",
        "price": 25.99,
        "currency": "$",
        "category": "Trousers"
    },
    {
        "id": 9,
        "image": "/img/products/n1.jpg",
        "create": "Malmö",
        "name": "Chest Pocket T-Shirt",
        "price": 38.99,
        "currency": "$",
        "category": "T-Shirts"
    },
    {
        "id": 10,
        "image": "/img/products/n2.jpg",
        "create": "Malmö",
        "name": "Two-Tone Pants",
        "price": 24.99,
        "currency": "$",
        "category": "Trousers"
    },
    {
        "id": 11,
        "image": "/img/products/n3.jpg",
        "create": "Malmö",
        "name": "Casual Loose Pants",
        "price": 24.99,
        "currency": "$",
        "category": "Trousers"
    },
    {
        "id": 12,
        "image": "/img/products/n4.jpg",
        "create": "Malmö",
        "name": "Striped Shirts",
        "price": 38.99,
        "currency": "$",
        "category": "Shirts"
    },
    {
        "id": 13,
        "image": "/img/products/n5.jpg",
        "create": "Malmö",
        "name": "Pineapple Set",
        "price": 58.99,
        "currency": "$",
        "category": "Sets"
    },
    {
        "id": 14,
        "image": "/img/products/n6.jpg",
        "create": "Malmö",
        "name": "Multi-Lines Set",
        "price": 58.99,
        "currency": "$",
        "category": "Sets"
    },
    {
        "id": 15,
        "image": "/img/products/n7.jpg",
        "create": "Malmö",
        "name": "Sunflower Up Shirts",
        "price": 38.99,
        "currency": "$",
        "category": "Shirts"
    },
    {
        "id": 16,
        "image": "/img/products/n8.jpg",
        "create": "Malmö",
        "name": "Sun & Moon Shirts",
        "price": 38.99,
        "currency": "$",
        "category": "Shirts"
    },
    {
        "id": 17,
        "image": "/img/products/n9.jpg",
        "create": "Malmö",
        "name": "Three Color T-Shirt",
        "price": 22.99,
        "currency": "$",
        "category": "T-Shirts"
    },
    {
        "id": 18,
        "image": "/img/products/n10.jpg",
        "create": "Malmö",
        "name": "Color Curve T-Shirt",
        "price": 22.99,
        "currency": "$",
        "category": "T-Shirts"
    },
    {
        "id": 19,
        "image": "/img/products/n11.jpg",
        "create": "Malmö",
        "name": "Tomorrow T-Shirt",
        "price": 24.99,
        "currency": "$",
        "category": "T-Shirts"
    },
    {
        "id": 20,
        "image": "/img/products/n12.jpg",
        "create": "Malmö",
        "name": "NASA T-Shirt",
        "price": 24.99,
        "currency": "$",
        "category": "T-Shirts"
    }
]